yahtzee_on_terminals/__init__.py
yahtzee_on_terminals/main.py
yahtzee_on_terminals/data/scoresheet.csv
yahtzee_on_terminal-0.0.3.dist-info/METADATA
yahtzee_on_terminal-0.0.3.dist-info/WHEEL
yahtzee_on_terminal-0.0.3.dist-info/licenses/LICENSE
yahtzee_on_terminal-0.0.3.dist-info/RECORD
